seats/__init__.py
seats/cli/__init__.py
seats/cli/cli.py
seats/cli/cmdbs/__init__.py
seats/cli/cmdbs/group.py
seats/cli/connectors/__init__.py
seats/cli/connectors/group.py
seats/cli/notebooks/__init__.py
seats/cli/notebooks/group.py
seats/clients/__init__.py
seats/cmdbs/__init__.py
seats/cmdbs/cmdb.py
seats/cmdbs/file.py
seats/connectors/__init__.py
seats/connectors/connector.py
seats/connectors/file.py
seats/connectors/fortigate/__init__.py
seats/connectors/fortigate/rest.py
seats/models/__init__.py
seats/models/customer.py
seats/notebooks/cmdb.json
seats/notebooks/cmdb_file.ipynb
seats/notebooks/connector_fortigate.ipynb
seats-0.1.4.dist-info/entry_points.txt
seats-0.1.4.dist-info/LICENSE
seats-0.1.4.dist-info/WHEEL
seats-0.1.4.dist-info/METADATA
seats-0.1.4.dist-info/RECORD
