Metadata-Version: 2.1
Name: seats
Version: 0.1.4
Summary: Security Engineering Automation Tool Set
Author: Thiago Takayama
Author-email: thiago@takayama.co.uk
Requires-Python: >=3.10,<4.0
Classifier: Programming Language :: Python :: 3
Classifier: Programming Language :: Python :: 3.10
Classifier: Programming Language :: Python :: 3.11
Provides-Extra: all
Provides-Extra: cli
Provides-Extra: flaskapp
Provides-Extra: notebooks
Requires-Dist: click (>=8.1.3,<9.0.0); extra == "all" or extra == "cli"
Requires-Dist: flask (>=2.2.2,<3.0.0); extra == "all" or extra == "flaskapp"
Requires-Dist: jupyter (>=1.0.0,<2.0.0); extra == "all" or extra == "notebooks"
Requires-Dist: pyyaml (>=6.0,<7.0)
Requires-Dist: requests (>=2.28.1,<3.0.0)
Requires-Dist: xmltodict (>=0.13.0,<0.14.0)
